mutwo/ekmelily_converters/__init__.py
mutwo/ekmelily_converters/configurations.py
mutwo/ekmelily_converters/constants.py
mutwo/ekmelily_converters/ekmelily.py
mutwo/ekmelily_version/__init__.py
mutwo.ekmelily-0.9.0.dist-info/LICENSE
mutwo.ekmelily-0.9.0.dist-info/METADATA
mutwo.ekmelily-0.9.0.dist-info/WHEEL
mutwo.ekmelily-0.9.0.dist-info/top_level.txt
mutwo.ekmelily-0.9.0.dist-info/RECORD
