Metadata-Version: 2.1
Name: mutwo.ekmelily
Version: 0.9.0
Summary: ekmelily extension for event based framework for generative art
Home-page: https://github.com/mutwo-org/mutwo.ekmelily
Author: Levin Eric Zimmermann
Author-email: levin.eric.zimmermann@posteo.eu
License: GPL
Project-URL: Documentation, https://mutwo-org.github.io
Requires-Python: >=3.10, <4
License-File: LICENSE
Requires-Dist: mutwo.core <3.0.0,>=2.0.0
Requires-Dist: mutwo.music <1.0.0,>=0.27.0
Provides-Extra: testing
Requires-Dist: pytest >=7.1.1 ; extra == 'testing'
